Module 2/Lab 32/Source_Code/async_fifo.v
module async_fifo #(
   parameter DEPTH = 8,
   parameter DATA_WIDTH = 8
)( 
   input                  wr_clk,
   input                  wr_rst,
   input                  wr_en,
   input [DATA_WIDTH-1:0] wr_data,
   output reg             wr_full,
   input                  rd_clk,
   input                  rd_rst,
   input                  rd_en,
   output reg [DATA_WIDTH-1:0] rd_data,
   output reg             rd_empty
);
  reg [DATA_WIDTH-1:0] mem [0:DEPTH-1];
  localparam PTR_WIDTH = $clog2(DEPTH);

 reg [PTR_WIDTH-1:0] wr_ptr = 0;
 reg [PTR_WIDTH-1:0] rd_ptr = 0;

 always @(posedge wr_clk or posedge wr_rst) begin
   if (wr_rst) begin
     wr_ptr <= 0;
     wr_full <= 0;
   end else if (wr_en && !wr_full) begin
     mem[wr_ptr] <= wr_data;
     wr_ptr <= wr_ptr + 1;
     wr_full <= ((wr_ptr + 1) == rd_ptr);
     end else begin
      wr_full <= ((wr_ptr + 1) == rd_ptr);
     end
   end
   always @(posedge rd_clk or posedge rd_rst) begin
     if (rd_rst) begin
       rd_ptr <= 0;
       rd_empty <= 1;
       rd_data <= 0;
     end else if (rd_en && !rd_empty) begin
       rd_data <= mem[rd_ptr];
       rd_ptr  <= rd_ptr + 1;
       rd_empty <= (rd_ptr + 1 ==wr_ptr);
     end else begin
       rd_empty <= (rd_ptr == wr_ptr);
     end
   end
endmodule

Module 2/Lab 32/Source_Code/block_b.v
module block_b (
  input rd_clk,
  input rd_rst,
  input rd_empty,
  input [7:0] rd_data,
  output reg rd_en
);
  always @(posedge rd_clk or posedge rd_rst) begin
    if (rd_rst) begin
      rd_en <= 0;
    end else begin
      rd_en <= !rd_empty;
    end
  end
endmodule

Module 2/Lab 32/Source_Code/block_a.v
module block_a (
  input wr_clk,
  input wr_rst,
  input wr_full,
  output reg wr_en,
  output reg[7:0] wr_data
);
  reg [7:0] counter = 0;
  always @(posedge wr_clk or posedge wr_rst) begin
    if (wr_rst) begin
      counter <= 0;
      wr_en <= 0;
    end else begin
      wr_en <= !wr_full;
      if (!wr_full) begin
        wr_data <= counter;
        counter <= counter + 1;
      end
    end
  end
endmodule

Module 2/Lab 32/Source_Code/top_multi_clk.v
module top_multi_clk(wr_clk, rd_clk, wr_rst, rd_rst);
   input wr_clk;
   input rd_clk;
   input wr_rst;
   input rd_rst;
  
   wire [7:0] wr_data, rd_data;
   wire wr_en, wr_full;
   wire rd_en, rd_empty;
  
   block_a producer (
      .wr_clk(wr_clk),
      .wr_rst(wr_rst),
      .wr_full(wr_full),
      .wr_en(wr_en),
      .wr_data(wr_data)
   );
   block_b consumer (
      .rd_clk(rd_clk),
      .rd_rst(rd_rst),
      .rd_empty(rd_empty),
      .rd_data(rd_data),
      .rd_en(rd_en)
   );
   async_fifo #(
   .DEPTH(8),
   .DATA_WIDTH(8)
   ) cdc_fifo (
     .wr_clk(wr_clk),
     .wr_rst(wr_rst),
     .wr_en(wr_en),
     .wr_data(wr_data),
     .wr_full(wr_full),
     .rd_clk(rd_clk),
     .rd_rst(rd_rst),
     .rd_en(rd_en),
     .rd_data(rd_data),
     .rd_empty(rd_empty)
   );
endmodule

Module 2/Lab 32/Testbench/multi_clk_tb.v
module multi_clk_tb;
reg wr_clk, rd_clk;
reg wr_rst, rd_rst;

always #5 wr_clk = ~wr_clk;
always #7 rd_clk = ~rd_clk;
 
top_multi_clk dut(.wr_clk(wr_clk),.rd_clk(rd_clk),.wr_rst(wr_rst),.rd_rst(rd_rst));
  initial begin
    $dumpfile("dump.vcd");
    $dumpvars(0, multi_clk_tb);
    wr_clk = 0;
    rd_clk = 0;

    wr_rst = 1;
    rd_rst = 1;

   #10 wr_rst = 0;
   #15 rd_rst = 0;
   #500 $finish;
  end
endmodule

Module 2/Lab 32/Waveforms/dump.vcd
$version Generated by VerilatedVcd $end
$timescale 1ps $end
 $scope module multi_clk_tb $end
  $var wire 1 4 wr_clk $end
  $var wire 1 5 rd_clk $end
  $var wire 1 6 wr_rst $end
  $var wire 1 7 rd_rst $end
  $scope module dut $end
   $var wire 1 4 wr_clk $end
   $var wire 1 5 rd_clk $end
   $var wire 1 6 wr_rst $end
   $var wire 1 7 rd_rst $end
   $var wire 8 # wr_data [7:0] $end
   $var wire 8 ' rd_data [7:0] $end
   $var wire 1 $ wr_en $end
   $var wire 1 % wr_full $end
   $var wire 1 ( rd_en $end
   $var wire 1 ) rd_empty $end
   $scope module cdc_fifo $end
    $var wire 32 8 DEPTH [31:0] $end
    $var wire 32 8 DATA_WIDTH [31:0] $end
    $var wire 1 4 wr_clk $end
    $var wire 1 6 wr_rst $end
    $var wire 1 $ wr_en $end
    $var wire 8 # wr_data [7:0] $end
    $var wire 1 % wr_full $end
    $var wire 1 5 rd_clk $end
    $var wire 1 7 rd_rst $end
    $var wire 1 ( rd_en $end
    $var wire 8 ' rd_data [7:0] $end
    $var wire 1 ) rd_empty $end
    $var wire 8 + mem[0] [7:0] $end
    $var wire 8 , mem[1] [7:0] $end
    $var wire 8 - mem[2] [7:0] $end
    $var wire 8 . mem[3] [7:0] $end
    $var wire 8 / mem[4] [7:0] $end
    $var wire 8 0 mem[5] [7:0] $end
    $var wire 8 1 mem[6] [7:0] $end
    $var wire 8 2 mem[7] [7:0] $end
    $var wire 32 9 PTR_WIDTH [31:0] $end
    $var wire 3 3 wr_ptr [2:0] $end
    $var wire 3 * rd_ptr [2:0] $end
   $upscope $end
   $scope module consumer $end
    $var wire 1 5 rd_clk $end
    $var wire 1 7 rd_rst $end
    $var wire 1 ) rd_empty $end
    $var wire 8 ' rd_data [7:0] $end
    $var wire 1 ( rd_en $end
   $upscope $end
   $scope module producer $end
    $var wire 1 4 wr_clk $end
    $var wire 1 6 wr_rst $end
    $var wire 1 % wr_full $end
    $var wire 1 $ wr_en $end
    $var wire 8 # wr_data [7:0] $end
    $var wire 8 & counter [7:0] $end
   $upscope $end
  $upscope $end
 $upscope $end
$enddefinitions $end


#0
b00000000 #
0$
0%
b00000000 &
b00000000 '
0(
1)
b000 *
b00000000 +
b00000000 ,
b00000000 -
b00000000 .
b00000000 /
b00000000 0
b00000000 1
b00000000 2
b000 3
04
05
16
17
b00000000000000000000000000001000 8
b00000000000000000000000000000011 9
#5
14
#7
15
#10
04
06
#14
05
#15
1$
b00000001 &
14
#20
04
#21
15
#25
b00000001 #
b00000010 &
b001 3
14
07
#28
05
#30
04
#35
b00000010 #
b00000011 &
0)
b00000001 ,
b010 3
14
15
#40
04
#42
05
#45
b00000011 #
b00000100 &
b00000010 -
b011 3
14
#49
1(
15
#50
04
#55
b00000100 #
b00000101 &
b00000011 .
b100 3
14
#56
05
#60
04
#63
b001 *
15
#65
b00000101 #
b00000110 &
b00000100 /
b101 3
14
#70
04
05
#75
b00000110 #
b00000111 &
b00000101 0
b110 3
14
#77
b00000001 '
b010 *
15
#80
04
#84
05
#85
b00000111 #
b00001000 &
b00000110 1
b111 3
14
#90
04
#91
b00000010 '
b011 *
15
#95
b00001000 #
b00001001 &
b00000111 2
b000 3
14
#98
05
#100
04
#105
b00001001 #
b00001010 &
b00000011 '
b100 *
b00001000 +
b001 3
14
15
#110
04
#112
05
#115
b00001010 #
b00001011 &
b00001001 ,
b010 3
14
#119
b00000100 '
b101 *
15
#120
04
#125
b00001011 #
b00001100 &
b00001010 -
b011 3
14
#126
05
#130
04
#133
b00000101 '
b110 *
15
#135
b00001100 #
b00001101 &
b00001011 .
b100 3
14
#140
04
05
#145
b00001101 #
b00001110 &
b00001100 /
b101 3
14
#147
b00000110 '
b111 *
15
#150
04
#154
05
#155
b00001110 #
b00001111 &
b00001101 0
b110 3
14
#160
04
#161
b00000111 '
b000 *
15
#165
b00001111 #
b00010000 &
b00001110 1
b111 3
14
#168
05
#170
04
#175
b00010000 #
b00010001 &
b00001000 '
b001 *
b00001111 2
b000 3
14
15
#180
04
#182
05
#185
b00010001 #
1%
b00010010 &
b00010000 +
b001 3
14
#189
b00001001 '
b010 *
15
#190
04
#195
0$
14
#196
05
#200
04
#203
b00001010 '
b011 *
15
#205
0%
14
#210
04
05
#215
b00010010 #
1$
b00010011 &
14
#217
b00001011 '
b100 *
15
#220
04
#224
05
#225
b00010011 #
b00010100 &
b00010010 ,
b010 3
14
#230
04
#231
b00001100 '
b101 *
15
#235
b00010100 #
b00010101 &
b00010011 -
b011 3
14
#238
05
#240
04
#245
b00010101 #
b00010110 &
b00001101 '
b110 *
b00010100 .
b100 3
14
15
#250
04
#252
05
#255
b00010110 #
b00010111 &
b00010101 /
b101 3
14
#259
b00001110 '
b111 *
15
#260
04
#265
b00010111 #
b00011000 &
b00010110 0
b110 3
14
#266
05
#270
04
#273
b00001111 '
b000 *
15
#275
b00011000 #
b00011001 &
b00010111 1
b111 3
14
#280
04
05
#285
b00011001 #
b00011010 &
b00011000 2
b000 3
14
#287
b00010000 '
b001 *
15
#290
04
#294
05
#295
b00011010 #
1%
b00011011 &
b00011001 +
b001 3
14
#300
04
#301
b00010010 '
b010 *
15
#305
0$
14
#308
05
#310
04
#315
b00010011 '
b011 *
14
15
#320
04
#322
05
#325
0%
14
#329
b00010100 '
b100 *
15
#330
04
#335
b00011011 #
1$
b00011100 &
14
#336
05
#340
04
#343
b00010101 '
b101 *
15
#345
b00011100 #
b00011101 &
b00011011 ,
b010 3
14
#350
04
05
#355
b00011101 #
b00011110 &
b00011100 -
b011 3
14
#357
b00010110 '
b110 *
15
#360
04
#364
05
#365
b00011110 #
b00011111 &
b00011101 .
b100 3
14
#370
04
#371
b00010111 '
b111 *
15
#375
b00011111 #
b00100000 &
b00011110 /
b101 3
14
#378
05
#380
04
#385
b00100000 #
b00100001 &
b00011000 '
b000 *
b00011111 0
b110 3
14
15
#390
04
#392
05
#395
b00100001 #
b00100010 &
b00100000 1
b111 3
14
#399
b00011001 '
b001 *
15
#400
04
#405
b00100010 #
b00100011 &
b00100001 2
b000 3
14
#406
05
#410
04
#413
b00011011 '
b010 *
15
#415
b00100011 #
b00100100 &
b00100010 +
b001 3
14
#420
04
05
#425
b00100100 #
1%
b00100101 &
b00100011 ,
b010 3
14
#427
b00011100 '
b011 *
15
#430
04
#434
05
#435
0$
14
#440
04
#441
b00011101 '
b100 *
15
#445
0%
14
#448
05
#450
04
#455
b00100101 #
1$
b00100110 &
b00011110 '
b101 *
14
15
#460
04
#462
05
#465
b00100110 #
b00100111 &
b00100101 -
b011 3
14
#469
b00011111 '
b110 *
15
#470
04
#475
b00100111 #
b00101000 &
b00100110 .
b100 3
14
#476
05
#480
04
#483
b00100000 '
b111 *
15
#485
b00101000 #
b00101001 &
b00100111 /
b101 3
14
#490
04
05
#495
b00101001 #
b00101010 &
b00101000 0
b110 3
14
#497
b00100001 '
b000 *
15
#500
04
#504
05
#505
b00101010 #
b00101011 &
b00101001 1
b111 3
14
#510
04
#511
b00100010 '
b001 *
15
#515
b00101011 #
b00101100 &
b00101010 2
b000 3
14
#518
05
#520
04
#525
b00101100 #
1%
b00101101 &
b00100011 '
b010 *
b00101011 +
b001 3
14
15
