Module 2/Lab 22/Source_Code/sync3_stage.v
module sync3_stage (
  input wire clk,
  input wire async_in,
  output reg sync_out );
  reg sync_ff1, sync_ff2;
  always @(posedge clk) begin
    sync_ff1  <= async_in;
    sync_ff2  <= sync_ff1;
    sync_out  <= sync_ff2;
  end
endmodule

Module 2/Lab 22/Source_Code/sync2_stage.v
module sync2_stage (
  input wire clk,
  input wire async_in,
  output reg sync_out
);
  reg sync_ff1;
  always @(posedge clk) begin
    sync_ff1  <= async_in;
    sync_out  <= sync_ff1;
  end
endmodule

Module 2/Lab 22/Testbench/sync_tb.v
module sync_tb;
  reg clk = 0;
  reg async_in = 0;
  wire sync_out2, sync_out3;
  always #5 clk = ~clk;

  sync2_stage u_sync2 (
    .clk(clk),
    .async_in(async_in),
    .sync_out(sync_out2)
);

sync3_stage u_sync3 (
  .clk(clk),
  .async_in(async_in),
  .sync_out(sync_out3) );
 initial begin
   $dumpfile("dump.vcd");
   $dumpvars(0, sync_tb);

   #7   async_in = 1;
   #13  async_in = 0;
   #8   async_in = 1;
   #12  async_in = 0;
   #50  $finish;
 end
endmodule

Module 2/Lab 22/Waveforms/dump.vcd
$version Generated by VerilatedVcd $end
$timescale 1ps $end
 $scope module sync_tb $end
  $var wire 1 ( clk $end
  $var wire 1 ) async_in $end
  $var wire 1 # sync_out2 $end
  $var wire 1 $ sync_out3 $end
  $scope module u_sync2 $end
   $var wire 1 ( clk $end
   $var wire 1 ) async_in $end
   $var wire 1 # sync_out $end
   $var wire 1 % sync_ff1 $end
  $upscope $end
  $scope module u_sync3 $end
   $var wire 1 ( clk $end
   $var wire 1 ) async_in $end
   $var wire 1 $ sync_out $end
   $var wire 1 & sync_ff1 $end
   $var wire 1 ' sync_ff2 $end
  $upscope $end
 $upscope $end
$enddefinitions $end


#0
0#
0$
0%
0&
0'
0(
0)
#5
1(
#7
1)
#10
0(
#15
1%
1&
1(
#20
0(
0)
#25
1#
0%
0&
1'
1(
#28
1)
#30
0(
#35
0#
1$
1%
1&
0'
1(
#40
0(
0)
#45
1#
0$
0%
0&
1'
1(
#50
0(
#55
0#
1$
0'
1(
#60
0(
#65
0$
1(
