Module 2/Lab 29/Source_Code/pos_edge_gating.v
module pos_latch_gating (
   input wire clk,
   input wire en,
   input wire rst,
   output reg  [3:0] count,
   output wire gated_clk
);
   reg en_latch;

   always @(clk or en) begin
       if (clk)
          en_latch = en;
   end
   assign gated_clk = clk & en_latch;
   always @(posedge gated_clk or posedge rst) begin
     if (rst)
        count <= 4'b0000;
     else
        count <= count + 1;
    end
endmodule

Module 2/Lab 29/Testbench/pos_latch_gating_tb.v
module pos_latch_gating_tb;
   reg clk = 0, en = 0, rst = 1;
   wire [3:0] count;
   wire gated_clk;
   pos_latch_gating uut (
       .clk(clk), .en(en), .rst(rst), 
       .count(count), .gated_clk(gated_clk)
);

always #5 clk =~clk;
initial begin 
   $dumpfile("pos_latch_gating.vcd");
   $dumpvars(0, pos_latch_gating_tb);
   
   #12 rst =0;
   #10 en = 1; #30 en = 0;
   #5  en = 1; #3  en = 0;
   #40 en = 1; #20 en = 0;
   #30 $finish;
 end
endmodule

Module 2/Lab 29/Waveforms/pos_latch_gating.vcd
$version Generated by VerilatedVcd $end
$timescale 1ps $end
 $scope module pos_latch_gating_tb $end
  $var wire 1 # clk $end
  $var wire 1 $ en $end
  $var wire 1 % rst $end
  $var wire 4 & count [3:0] $end
  $var wire 1 ' gated_clk $end
  $scope module uut $end
   $var wire 1 # clk $end
   $var wire 1 $ en $end
   $var wire 1 % rst $end
   $var wire 4 & count [3:0] $end
   $var wire 1 ' gated_clk $end
   $var wire 1 ( en_latch $end
  $upscope $end
 $upscope $end
$enddefinitions $end


#0
0#
0$
1%
b0000 &
0'
0(
#5
1#
#10
0#
#12
0%
#15
1#
#20
0#
#22
1$
#25
1#
b0001 &
1'
1(
#30
0#
0'
#35
1#
b0010 &
1'
#40
0#
0'
#45
1#
b0011 &
1'
#50
0#
0'
#52
0$
#55
1#
0(
#57
1$
b0100 &
1'
1(
#60
0#
0$
0'
#65
1#
0(
#70
0#
#75
1#
#80
0#
#85
1#
#90
0#
#95
1#
#100
0#
1$
#105
1#
b0101 &
1'
1(
#110
0#
0'
#115
1#
b0110 &
1'
#120
0#
0$
0'
#125
1#
0(
