Module 2/Lab 30/Source_Code/reset_stretch.v
module reset_stretch2 (
    input wire clk,
    input wire arst_n,
    output wire srst_n
);
    reg [1:0] hold_cnt;
    reg       hold;
    always @(posedge clk or negedge arst_n) begin
        if (!arst_n) begin
           hold      <= 1'b1;
           hold_cnt  <= 2'b0;
        end else if (hold) begin
            if (hold_cnt == 2)
                hold <= 1'b0;
            else
                hold_cnt <= hold_cnt + 1'b1;
        end
  end
  assign srst_n = ~hold;
endmodule

Module 2/Lab 30/Source_Code/reset_top.v
module reset_top (
    input wire clk,
    input wire arst_n,
    output wire [7:0] count,    
    output wire srst_n
);
   reset_stretch2 u_rst (
       .clk(clk),
       .arst_n(arst_n),
       .srst_n(srst_n)
   );
   reg [7:0] cnt_q;
   always @(posedge clk or negedge srst_n) begin
       if (!srst_n)
           cnt_q <= 8'h00;
       else
           cnt_q <= cnt_q + 1;
   end
   assign count = cnt_q;
endmodule

Module 2/Lab 30/Testbench/reset_top_tb.v
`timescale 1ns/1ps
module reset_top_tb;
    reg clk = 0;
    reg arst_n = 1;
    wire [7:0] count;
    wire srst_n;
    reset_top dut (
         .clk(clk),
         .arst_n(arst_n),
         .count(count),
         .srst_n(srst_n)
    );
    always #5 clk = ~clk;
    initial begin
        $dumpfile("reset_stretch2.vcd");
        $dumpvars(0, reset_top_tb);
        #7  arst_n = 0;
        #11 arst_n = 1;
        #100;
        #3  arst_n = 0;
        #12 arst_n = 1;
        #120 $finish;
    end
endmodule

Module 2/Lab 30/Waveforms/reset_stretch2.vcd
$version Generated by VerilatedVcd $end
$timescale 1ps $end
 $scope module reset_top_tb $end
  $var wire 1 & clk $end
  $var wire 1 ' arst_n $end
  $var wire 8 ( count [7:0] $end
  $var wire 1 # srst_n $end
  $scope module dut $end
   $var wire 1 & clk $end
   $var wire 1 ' arst_n $end
   $var wire 8 ( count [7:0] $end
   $var wire 1 # srst_n $end
   $var wire 8 ( cnt_q [7:0] $end
   $scope module u_rst $end
    $var wire 1 & clk $end
    $var wire 1 ' arst_n $end
    $var wire 1 # srst_n $end
    $var wire 2 $ hold_cnt [1:0] $end
    $var wire 1 % hold $end
   $upscope $end
  $upscope $end
 $upscope $end
$enddefinitions $end


#0
1#
b00 $
0%
0&
1'
b00000000 (
#5000
1&
b00000001 (
#7000
0#
1%
0'
b00000000 (
#10000
0&
#15000
1&
#18000
1'
#20000
0&
#25000
b01 $
1&
#30000
0&
#35000
b10 $
1&
#40000
0&
#45000
1#
0%
1&
#50000
0&
#55000
1&
b00000001 (
#60000
0&
#65000
1&
b00000010 (
#70000
0&
#75000
1&
b00000011 (
#80000
0&
#85000
1&
b00000100 (
#90000
0&
#95000
1&
b00000101 (
#100000
0&
#105000
1&
b00000110 (
#110000
0&
#115000
1&
b00000111 (
#120000
0&
#121000
0#
b00 $
1%
0'
b00000000 (
#125000
1&
#130000
0&
#133000
1'
#135000
b01 $
1&
#140000
0&
#145000
b10 $
1&
#150000
0&
#155000
1#
0%
1&
#160000
0&
#165000
1&
b00000001 (
#170000
0&
#175000
1&
b00000010 (
#180000
0&
#185000
1&
b00000011 (
#190000
0&
#195000
1&
b00000100 (
#200000
0&
#205000
1&
b00000101 (
#210000
0&
#215000
1&
b00000110 (
#220000
0&
#225000
1&
b00000111 (
#230000
0&
#235000
1&
b00001000 (
#240000
0&
#245000
1&
b00001001 (
