Module 2/Lab 31/Source_Code/optimized_fsm.v
module optimized_fsm (
  input clk,
  input rst,
  input start,
  output reg [1:0] state,
  output reg done
);
  always @(posedge clk or posedge rst) begin
    if (rst) begin
      state <= 0;
      done  <= 0;
    end else begin
       case (state)
         0: if (start) state <= 1;
         1: state <= 2;
         2: begin
            done <= 1;
            state <= 3;
       end
     endcase
   end
 end
endmodule

Module 2/Lab 31/Source_Code/inefficient_fsm.v
module inefficient_fsm (
   input clk,
   input rst,
   input start,
   output reg [1:0] state,
   output reg done
);
  always @(posedge clk or posedge rst) begin
    if (rst) begin
      state <= 0;
      done  <= 0;
    end else begin
      state <= state +1;
      if (state == 2)
        done <= 1;
    end
 end
endmodule

Module 2/Lab 31/Testbench/fsm_tb.v
module fsm_tb;

   reg clk = 0;
   reg rst = 1;
   reg start = 0;
   wire [1:0] state_inefficient, state_optimized;
   wire done_inefficient, done_optimized;
   
   always #5 clk = ~clk;
   
   inefficient_fsm u_bad (
     .clk(clk), .rst(rst), .start(start),
     .state(state_inefficient), .done(done_inefficient)
);

optimized_fsm u_opt (
   .clk(clk), .rst(rst), .start(start),
   .state(state_optimized), .done(done_optimized)
);

initial begin
   $dumpfile("dump.vcd");
   $dumpvars(0, fsm_tb);
  
   #12 rst = 0;
   #10 start = 1;
   #20 start = 0;
   #100 $finish;
end
endmodule

Module 2/Lab 31/Waveforms/dump.vcd
$version Generated by VerilatedVcd $end
$timescale 1ps $end
 $scope module fsm_tb $end
  $var wire 1 ' clk $end
  $var wire 1 ( rst $end
  $var wire 1 ) start $end
  $var wire 2 # state_inefficient [1:0] $end
  $var wire 2 $ state_optimized [1:0] $end
  $var wire 1 % done_inefficient $end
  $var wire 1 & done_optimized $end
  $scope module u_bad $end
   $var wire 1 ' clk $end
   $var wire 1 ( rst $end
   $var wire 1 ) start $end
   $var wire 2 # state [1:0] $end
   $var wire 1 % done $end
  $upscope $end
  $scope module u_opt $end
   $var wire 1 ' clk $end
   $var wire 1 ( rst $end
   $var wire 1 ) start $end
   $var wire 2 $ state [1:0] $end
   $var wire 1 & done $end
  $upscope $end
 $upscope $end
$enddefinitions $end


#0
b00 #
b00 $
0%
0&
0'
1(
0)
#5
1'
#10
0'
#12
0(
#15
b01 #
1'
#20
0'
#22
1)
#25
b10 #
b01 $
1'
#30
0'
#35
b11 #
b10 $
1%
1'
#40
0'
#42
0)
#45
b00 #
b11 $
1&
1'
#50
0'
#55
b01 #
1'
#60
0'
#65
b10 #
1'
#70
0'
#75
b11 #
1'
#80
0'
#85
b00 #
1'
#90
0'
#95
b01 #
1'
#100
0'
#105
b10 #
1'
#110
0'
#115
b11 #
1'
#120
0'
#125
b00 #
1'
#130
0'
#135
b01 #
1'
