Module 2/Lab 28/Source_Code/async_fifo.v
module async_fifo #(
     parameter DEPTH = 4,
     parameter ADDR_WIDTH = 2
) (
    input wire       wr_clk,
    input wire       wr_en,
    input wire [7:0] wr_data,
    output wire      full,
    input wire       rd_clk,
    input wire       rd_en,
    output reg [7:0] rd_data,
    output wire      empty,
    input wire       rst_n
);
  reg [7:0] mem[0:DEPTH-1];
  reg [ADDR_WIDTH:0] wr_ptr = 0;
  reg [ADDR_WIDTH:0] rd_ptr = 0;
always @(posedge wr_clk or negedge rst_n) begin
    if (!rst_n)
       wr_ptr <= 0;
    else if (wr_en && !full) begin
       mem[wr_ptr[ADDR_WIDTH-1:0]] <= wr_data;
       wr_ptr <= wr_ptr + 1;
    end
  end
always@(posedge rd_clk or negedge rst_n) begin
    if (!rst_n) begin
       rd_ptr <= 0;
       rd_data <= 8'h00;
    end else if (rd_en && !empty) begin
       rd_data <= mem[rd_ptr[ADDR_WIDTH-1:0]];
       rd_ptr  <= rd_ptr + 1;
    end
  end
assign full  = (wr_ptr[ADDR_WIDTH] !=rd_ptr[ADDR_WIDTH]) && (wr_ptr[ADDR_WIDTH-1:0] == rd_ptr[ADDR_WIDTH-1:0]);
assign empty = (wr_ptr == rd_ptr);
endmodule

Module 2/Lab 28/Testbench/async_fifo_tb.v
`timescale 1ns/1ps
module async_fifo_tb;
   reg wr_clk = 0;
   reg rd_clk = 0;
   reg rst_n  = 0;
   reg       wr_en = 0;
   reg [7:0] wr_data = 0;
   wire      full;
   reg       rd_en = 0;
   wire [7:0] rd_data;
   wire empty;
  async_fifo uut  (
   .wr_clk(wr_clk), .wr_en(wr_en), .wr_data(wr_data),  .full(full), .rd_clk(rd_clk), .rd_en(rd_en), .rd_data(rd_data),
   .empty(empty), .rst_n(rst_n) 
);

always #4 wr_clk = ~wr_clk;
always #7 rd_clk = ~rd_clk;

initial begin
   $dumpfile("async_fifo.vcd");
   $dumpvars(0, async_fifo_tb);
   #5 rst_n = 1;
   repeat (4) begin
   @(posedge wr_clk);
   if (!full) begin
                 wr_en   <= 1;
                 wr_data <= wr_data + 1;
              end
           end
           wr_en <= 0;
           repeat (4) begin
              @(posedge rd_clk);
              if (!empty) rd_en <= 1;
              @(posedge rd_clk);
              rd_en <= 0;
           end
           #50 $finish;
       end
endmodule

Module 2/Lab 28/Waveforms/async_fifo.vcd
$version Generated by VerilatedVcd $end
$timescale 1ps $end
 $scope module async_fifo_tb $end
  $var wire 1 ( wr_clk $end
  $var wire 1 ) rd_clk $end
  $var wire 1 * rst_n $end
  $var wire 1 + wr_en $end
  $var wire 8 , wr_data [7:0] $end
  $var wire 1 - full $end
  $var wire 1 . rd_en $end
  $var wire 8 / rd_data [7:0] $end
  $var wire 1 0 empty $end
  $scope module uut $end
   $var wire 32 2 DEPTH [31:0] $end
   $var wire 32 3 ADDR_WIDTH [31:0] $end
   $var wire 1 ( wr_clk $end
   $var wire 1 + wr_en $end
   $var wire 8 , wr_data [7:0] $end
   $var wire 1 - full $end
   $var wire 1 ) rd_clk $end
   $var wire 1 . rd_en $end
   $var wire 8 / rd_data [7:0] $end
   $var wire 1 0 empty $end
   $var wire 1 * rst_n $end
   $var wire 8 # mem[0] [7:0] $end
   $var wire 8 $ mem[1] [7:0] $end
   $var wire 8 % mem[2] [7:0] $end
   $var wire 8 & mem[3] [7:0] $end
   $var wire 3 ' wr_ptr [2:0] $end
   $var wire 3 1 rd_ptr [2:0] $end
  $upscope $end
 $upscope $end
$enddefinitions $end


#0
b00000000 #
b00000000 $
b00000000 %
b00000000 &
b000 '
0(
0)
0*
0+
b00000000 ,
0-
0.
b00000000 /
10
b000 1
b00000000000000000000000000000100 2
b00000000000000000000000000000010 3
#4000
1(
#5000
1*
#7000
1)
#8000
0(
#12000
b00000001 #
b001 '
1(
1+
b00000001 ,
00
#14000
0)
#16000
0(
#20000
b00000010 $
b010 '
1(
b00000010 ,
#21000
1)
#24000
0(
#28000
b00000011 %
b011 '
1(
0)
b00000011 ,
#32000
0(
#35000
1)
#36000
1(
0+
b00000100 ,
#40000
0(
#42000
0)
#44000
1(
#48000
0(
#49000
1)
1.
b00000001 /
b001 1
#52000
1(
#56000
0(
0)
#60000
1(
#63000
1)
0.
#64000
0(
#68000
1(
#70000
0)
#72000
0(
#76000
1(
#77000
1)
1.
b00000010 /
b010 1
#80000
0(
#84000
1(
0)
#88000
0(
#91000
1)
0.
#92000
1(
#96000
0(
#98000
0)
#100000
1(
#104000
0(
#105000
1)
1.
b00000011 /
10
b011 1
#108000
1(
#112000
0(
0)
#116000
1(
#119000
1)
0.
