Module 2/Lab 24/Source_Code/clk_mux.v
module clk_mux (
  input clk0,
  input clk1,
  input sel,
  output clk_out
);
  assign clk_out = (sel == 1'b0)? clk0: clk1;
endmodule

Module 2/Lab 24/Source_Code/clk_divider.v
module clk_divider (
  input clk_in,
  input rst,
  output reg clk_out
);
  reg [1:0] counter;
  always @(posedge clk_in or posedge rst) begin
    if (rst) begin
      counter <= 2'b0;
      clk_out <= 0;
    end else begin
      counter <= counter + 1;
      if (counter == 2'b11)
      clk_out <= ~clk_out;
    end
  end
endmodule

Module 2/Lab 24/Testbench/multi_clk_tb.v
module multi_clk_tb;
  reg clk_fast = 0;
  reg clk_slow = 0;
  reg rst = 1;
  reg sel = 0;
  wire muxed_clk;
  wire clk_div4;
  always #5 clk_fast  = ~clk_fast;
  always #10 clk_slow = ~clk_slow;
  clk_divider u_div (
    .clk_in(clk_fast),
    .rst(rst),
    .clk_out(clk_div4)
);
 clk_mux u_mux (
   .clk0(clk_fast),
   .clk1(clk_slow),
   .sel(sel),
   .clk_out(muxed_clk)
);
initial begin
  $dumpfile("dump.vcd");
  $dumpvars(0, multi_clk_tb);
  #15 rst = 0;
  #60 sel = 1;
  #60 sel = 0;
  #100 $finish;
 end
endmodule

Module 2/Lab 24/Waveforms/dump.vcd
$version Generated by VerilatedVcd $end
$timescale 1ps $end
 $scope module multi_clk_tb $end
  $var wire 1 # clk_fast $end
  $var wire 1 $ clk_slow $end
  $var wire 1 % rst $end
  $var wire 1 & sel $end
  $var wire 1 ' muxed_clk $end
  $var wire 1 ( clk_div4 $end
  $scope module u_div $end
   $var wire 1 # clk_in $end
   $var wire 1 % rst $end
   $var wire 1 ( clk_out $end
   $var wire 2 ) counter [1:0] $end
  $upscope $end
  $scope module u_mux $end
   $var wire 1 # clk0 $end
   $var wire 1 $ clk1 $end
   $var wire 1 & sel $end
   $var wire 1 ' clk_out $end
  $upscope $end
 $upscope $end
$enddefinitions $end


#0
0#
0$
1%
0&
0'
0(
b00 )
#5
1#
1'
#10
0#
1$
0'
#15
1#
0%
1'
b01 )
#20
0#
0$
0'
#25
1#
1'
b10 )
#30
0#
1$
0'
#35
1#
1'
b11 )
#40
0#
0$
0'
#45
1#
1'
1(
b00 )
#50
0#
1$
0'
#55
1#
1'
b01 )
#60
0#
0$
0'
#65
1#
1'
b10 )
#70
0#
1$
0'
#75
1#
1&
1'
b11 )
#80
0#
0$
0'
#85
1#
0(
b00 )
#90
0#
1$
1'
#95
1#
b01 )
#100
0#
0$
0'
#105
1#
b10 )
#110
0#
1$
1'
#115
1#
b11 )
#120
0#
0$
0'
#125
1#
1(
b00 )
#130
0#
1$
1'
#135
1#
0&
b01 )
#140
0#
0$
0'
#145
1#
1'
b10 )
#150
0#
1$
0'
#155
1#
1'
b11 )
#160
0#
0$
0'
#165
1#
1'
0(
b00 )
#170
0#
1$
0'
#175
1#
1'
b01 )
#180
0#
0$
0'
#185
1#
1'
b10 )
#190
0#
1$
0'
#195
1#
1'
b11 )
#200
0#
0$
0'
#205
1#
1'
1(
b00 )
#210
0#
1$
0'
#215
1#
1'
b01 )
#220
0#
0$
0'
#225
1#
1'
b10 )
#230
0#
1$
0'
#235
1#
1'
b11 )
